repo2context/__init__.py
repo2context/cli.py
repo2context/core.py
repo2context/utils.py
repo2context-0.1.0.dist-info/LICENSE
repo2context-0.1.0.dist-info/METADATA
repo2context-0.1.0.dist-info/WHEEL
repo2context-0.1.0.dist-info/entry_points.txt
repo2context-0.1.0.dist-info/RECORD
