Metadata-Version: 2.3
Name: repo2context
Version: 0.1.0
Summary: One-command repo → Markdown context generator for LLM workflows
License: MIT
Keywords: llm,context,repository,markdown,cli
Author: Your Name
Author-email: your.email@example.com
Requires-Python: >=3.11,<4.0
Classifier: Development Status :: 4 - Beta
Classifier: Environment :: Console
Classifier: Intended Audience :: Developers
Classifier: License :: OSI Approved :: MIT License
Classifier: Operating System :: OS Independent
Classifier: Programming Language :: Python :: 3
Classifier: Programming Language :: Python :: 3.11
Classifier: Programming Language :: Python :: 3.12
Classifier: Programming Language :: Python :: 3.13
Classifier: Topic :: Text Processing :: Markup
Classifier: Topic :: Utilities
Provides-Extra: all
Provides-Extra: summary
Provides-Extra: tiktoken
Requires-Dist: openai (>=1.0.0,<2.0.0) ; extra == "summary" or extra == "all"
Requires-Dist: pathspec (>=0.11.0,<0.12.0)
Requires-Dist: tiktoken (>=0.5.0,<0.6.0) ; extra == "tiktoken" or extra == "all"
Project-URL: Repository, https://github.com/AdiMilstein/repo2context
